dlna/__init__.py
dlna/client.py
dlna/util.py
dlna/templates/action-Play.xml
dlna/templates/action-SetAVTransportURI.xml
dlna-0.2.2.dist-info/LICENSE
dlna-0.2.2.dist-info/METADATA
dlna-0.2.2.dist-info/WHEEL
dlna-0.2.2.dist-info/entry_points.txt
dlna-0.2.2.dist-info/top_level.txt
dlna-0.2.2.dist-info/RECORD
