Metadata-Version: 2.1
Name: dlna
Version: 0.2.2
Summary: A UPnP/DLNA client, support local file and online resource cast to screen.
Home-page: https://leesoar.com/real
Author: leesoar
Author-email: core@111.com
License: MIT
Keywords: dlna
Platform: UNKNOWN
Classifier: License :: OSI Approved :: MIT License
Classifier: Programming Language :: Python :: 3.5
Classifier: Programming Language :: Python :: 3.6
Classifier: Programming Language :: Python :: 3.7
Classifier: Programming Language :: Python :: Implementation :: CPython
Classifier: Programming Language :: Python :: Implementation :: PyPy
Requires-Python: >=3.3.0
Requires-Dist: lxml
Requires-Dist: requests
Requires-Dist: Twisted
Requires-Dist: urllib3
